facets_overview/__init__.py
facets_overview/base_feature_statistics_generator.py
facets_overview/base_generic_feature_statistics_generator.py
facets_overview/feature_statistics_generator.py
facets_overview/feature_statistics_generator_test.py
facets_overview/feature_statistics_pb2.py
facets_overview/generic_feature_statistics_generator.py
facets_overview/generic_feature_statistics_generator_test.py
facets_overview-1.1.1.dist-info/METADATA
facets_overview-1.1.1.dist-info/WHEEL
facets_overview-1.1.1.dist-info/top_level.txt
facets_overview-1.1.1.dist-info/RECORD
