Metadata-Version: 2.1
Name: facets-overview
Version: 1.1.1
Summary: Python code to support the Facets Overview visualization
Home-page: http://github.com/pair-code/facets
Author: Google Inc.
Author-email: opensource@google.com
License: Apache 2.0
Requires-Dist: numpy (>=1.16.0)
Requires-Dist: pandas (>=0.22.0)
Requires-Dist: protobuf (>=3.20.0)
